nanofoot/__init__.py
nanofoot/api.py
nanofoot/constants.py
nanofoot/exercises.py
nanofoot/fileserver.py
nanofoot/folders.py
nanofoot/video.py
nanofoot/cli/__init__.py
nanofoot/cli/video.py
nanofootball_sdk-0.1.0.dist-info/METADATA
nanofootball_sdk-0.1.0.dist-info/WHEEL
nanofootball_sdk-0.1.0.dist-info/entry_points.txt
nanofootball_sdk-0.1.0.dist-info/top_level.txt
nanofootball_sdk-0.1.0.dist-info/RECORD
