Metadata-Version: 2.1
Name: nanofootball-sdk
Version: 0.1.0
Home-page: https://github.com/thefrol/nanofootball-sdk
License: MIT
Requires-Dist: pyyaml
Requires-Dist: bs4
Requires-Dist: requests
